{
  "name": [
    {
      "value": "Diplodocus"
    }
  ],
  "appearance": [
    {
      "value": "<p>25 mètres pour environ 25 tonnes, le diplodocus est un géant parmi les géants.</p>\r\n",
      "format": "simple_html"
    }
  ],
  "description": [
    {
      "value": "<p>Heureusement, il s’agit d’un herbivore plutôt placide.</p>\r\n",
      "format": "simple_html"
    }
  ],
  "creature_family": [
    {
      "target_id": "10",
      "label": "Dinosaures"
    }
  ],
  "environment": [
    {
      "value": "plain",
      "label": "Plaine"
    }
  ],
  "archetype": [
    {
      "value": "standard",
      "label": "Standard"
    }
  ],
  "boss_type": [],
  "boss_rank": [],
  "level": [
    {
      "value": "12"
    }
  ],
  "category": [
    {
      "value": "alive",
      "label": "Vivante"
    }
  ],
  "size": [
    {
      "value": "colossal",
      "label": "Colossale"
    }
  ],
  "str_mod": [
    {
      "value": "15"
    }
  ],
  "str_comment": [],
  "dex_mod": [
    {
      "value": "0"
    }
  ],
  "dex_comment": [],
  "con_mod": [
    {
      "value": "15"
    }
  ],
  "con_comment": [],
  "int_mod": [
    {
      "value": "-4"
    }
  ],
  "int_comment": [],
  "wis_mod": [
    {
      "value": "0"
    }
  ],
  "wis_comment": [],
  "cha_mod": [
    {
      "value": "-2"
    }
  ],
  "cha_comment": [],
  "sup_abilities": [
    {
      "value": "str",
      "label": "FOR"
    }
  ],
  "defense": [
    {
      "value": "26"
    }
  ],
  "health_point": [
    {
      "value": "200"
    }
  ],
  "dmg_reduction": [],
  "init": [
    {
      "value": "10"
    }
  ],
  "attacks": [
    {
      "value": "<p><strong>Queue</strong> +21 <strong>DM</strong> 3d6+15</p>\r\n",
      "format": "simple_html",
      "data": [
        {
          "name": "Queue",
          "test": "+21",
          "dm": "3d6+15",
          "special": null,
          "reach": null
        }
      ]
    }
  ],
  "profile": [],
  "profile_level": [],
  "paths": [
    {
      "value": "<p><strong>Voie du colosse</strong> rang 3</p>\r\n",
      "format": "simple_html"
    }
  ],
  "special_capabilities": [
    {
      "value": null,
      "format": null
    }
  ],
  "comments": [
    {
      "value": null,
      "format": null
    }
  ],
  "structured_capabilities": {
    "91": {
      "id": "91",
      "name": "Voie du colosse",
      "type": "creature",
      "capabilities": {
        "1": {
          "target_id": "414",
          "label": "Fauchage",
          "rank": "1",
          "is_limited": "0",
          "is_magical": "0",
          "description": "Sur 15 à 20 au test d’attaque, si l’attaque est réussie, la victime doit réussir au choix un test de FOR ou de DEX difficulté [10+Mod. de FOR de la créature] ou être Renversée. La créature retranche 2 à tous les DM subis (RD 2) avec des armes (contact ou distance). Les sorts font des DM normaux.\r\n"
        },
        "2": {
          "target_id": "415",
          "label": "Balayage",
          "rank": "2",
          "is_limited": "0",
          "is_magical": "0",
          "description": "La créature utilise sa grande taille pour affecter plusieurs créatures face à elle d’un seul coup de patte/arme. Si plusieurs cibles sont présentes face à elle, son attaque affecte deux créatures (dans un arc de 180°). Faire un seul test d’attaque et le comparer à la DEF de chaque cible. Sa résistance aux DM passe à 4 (RD 4).\r\n"
        },
        "3": {
          "target_id": "416",
          "label": "Projection",
          "rank": "3",
          "is_limited": "0",
          "is_magical": "0",
          "description": "Sur 15 à 20 au test d’attaque, la victime est projetée à [1d6+1] mètres de là (plus ou moins selon la taille des protagonistes) et subit +3d6 DM supplémentaires. Elle doit réussir un test de CON de difficulté 15 ou être Étourdie. A chaque tour elle peut tenter un nouveau test de CON pour retrouver ses esprits. Sa résistance aux DM passe à 6 (RD 6).\r\n"
        }
      },
      "rank": 3
    }
  },
  "capabilities": [
    {
      "target_id": "414",
      "label": "Fauchage",
      "rank": "1",
      "is_limited": "0",
      "is_magical": "0",
      "description": "Sur 15 à 20 au test d’attaque, si l’attaque est réussie, la victime doit réussir au choix un test de FOR ou de DEX difficulté [10+Mod. de FOR de la créature] ou être Renversée. La créature retranche 2 à tous les DM subis (RD 2) avec des armes (contact ou distance). Les sorts font des DM normaux.\r\n",
      "paths": "Voie du colosse"
    },
    {
      "target_id": "415",
      "label": "Balayage",
      "rank": "2",
      "is_limited": "0",
      "is_magical": "0",
      "description": "La créature utilise sa grande taille pour affecter plusieurs créatures face à elle d’un seul coup de patte/arme. Si plusieurs cibles sont présentes face à elle, son attaque affecte deux créatures (dans un arc de 180°). Faire un seul test d’attaque et le comparer à la DEF de chaque cible. Sa résistance aux DM passe à 4 (RD 4).\r\n",
      "paths": "Voie du colosse"
    },
    {
      "target_id": "416",
      "label": "Projection",
      "rank": "3",
      "is_limited": "0",
      "is_magical": "0",
      "description": "Sur 15 à 20 au test d’attaque, la victime est projetée à [1d6+1] mètres de là (plus ou moins selon la taille des protagonistes) et subit +3d6 DM supplémentaires. Elle doit réussir un test de CON de difficulté 15 ou être Étourdie. A chaque tour elle peut tenter un nouveau test de CON pour retrouver ses esprits. Sa résistance aux DM passe à 6 (RD 6).\r\n",
      "paths": "Voie du colosse"
    }
  ],
  "picture": [
    {
      "target_id": "971",
      "alt": "Diplodocus",
      "title": "",
      "width": "1024",
      "height": "1024",
      "label": "diplodocus-modified.png",
      "creature_token_url": "https://www.co-drs.org/sites/default/files/styles/creatures_token/public/co/creature/2023-02/diplodocus-modified.png.webp?itok=uvail7UX"
    }
  ]
}