{
  "name": [
    {
      "value": "Sergent Orque noir"
    }
  ],
  "appearance": [
    {
      "value": null,
      "format": null
    }
  ],
  "description": [
    {
      "value": "<p>Les orques noirs sont une race d’orques d’élite obtenus par la sélection et la reproduction de puissant maîtres maléfiques souhaitant construire l’armée ultime. Leur peau est plus sombre et leur musculature plus imposante. Ils manient des armes à 2 mains.</p>\r\n",
      "format": "simple_html"
    }
  ],
  "creature_family": [
    {
      "target_id": "37",
      "label": "Orques"
    }
  ],
  "environment": [
    {
      "value": "underground",
      "label": "Souterrain"
    }
  ],
  "archetype": [
    {
      "value": "powerful",
      "label": "Puissant"
    }
  ],
  "boss_type": [],
  "boss_rank": [],
  "level": [
    {
      "value": "2"
    }
  ],
  "category": [
    {
      "value": "humanoid",
      "label": "Humanoïde"
    }
  ],
  "size": [
    {
      "value": "medium",
      "label": "Moyen"
    }
  ],
  "str_mod": [
    {
      "value": "4"
    }
  ],
  "str_comment": [],
  "dex_mod": [
    {
      "value": "0"
    }
  ],
  "dex_comment": [],
  "con_mod": [
    {
      "value": "3"
    }
  ],
  "con_comment": [],
  "int_mod": [
    {
      "value": "-2"
    }
  ],
  "int_comment": [],
  "wis_mod": [
    {
      "value": "0"
    }
  ],
  "wis_comment": [],
  "cha_mod": [
    {
      "value": "0"
    }
  ],
  "cha_comment": [],
  "sup_abilities": [
    {
      "value": "str",
      "label": "FOR"
    }
  ],
  "defense": [
    {
      "value": "16"
    }
  ],
  "health_point": [
    {
      "value": "35"
    }
  ],
  "dmg_reduction": [],
  "init": [
    {
      "value": "8"
    }
  ],
  "attacks": [
    {
      "value": "<p><strong>Épée 2 mains</strong> +7 <strong>DM</strong> 2d6+4</p>\r\n",
      "format": "simple_html",
      "data": [
        {
          "name": "Épée 2 mains",
          "test": "+7",
          "dm": "2d6+4",
          "special": null,
          "reach": null
        }
      ]
    }
  ],
  "profile": [],
  "profile_level": [],
  "paths": [
    {
      "value": null,
      "format": null
    }
  ],
  "special_capabilities": [
    {
      "value": "<p><em>Sensible à la lumière :</em> créatures souterraines, les orques détestent la lumière du jour. La lumière du soleil leur inflige une pénalité de -1 en attaque.</p>\r\n",
      "format": "simple_html"
    }
  ],
  "comments": [
    {
      "value": null,
      "format": null
    }
  ],
  "structured_capabilities": [],
  "capabilities": [],
  "picture": []
}